zein/__init__.py
zein/retrained_labels.txt
zein/data/data.csv
zein/images/__init__.py
zein/images/_utils.py
zein/images/images_module.py
zein/models/prompt_svm_model.pkl
zein/models/prompt_vectorizer.pkl
zein/models/svm_model.pkl
zein/models/vectorizer.pkl
zein/text/__init__.py
zein/text/_utils.py
zein/text/ar.py
zein/text/text_module.py
zein-1.0.1.dist-info/LICENSE
zein-1.0.1.dist-info/METADATA
zein-1.0.1.dist-info/WHEEL
zein-1.0.1.dist-info/top_level.txt
zein-1.0.1.dist-info/RECORD
