Metadata-Version: 2.1
Name: zein
Version: 1.0.1
Summary: A python library for ensuring the safety and security of visual content
Home-page: UNKNOWN
Author: Mohamed Elsayed
Author-email: <mohamedelsayed3487@gmail.com>
License: UNKNOWN
Keywords: python,arabic filtering,text filtering,profanity check
Platform: UNKNOWN
Classifier: Development Status :: 1 - Planning
Classifier: Intended Audience :: Developers
Classifier: Programming Language :: Python :: 3
Classifier: Operating System :: Unix
Classifier: Operating System :: MacOS :: MacOS X
Classifier: Operating System :: Microsoft :: Windows
License-File: LICENSE
Requires-Dist: pandas
Requires-Dist: joblib
Requires-Dist: tensorflow
Requires-Dist: scikit-learn (>=0.24.2)
